{"type":"PR","pr":{"number":20,"head":"c7913665ab55f4dc85cb476de414a3937c71bfbe"},"user":"marusho","status":"draft","branch":"cms/blog/2021-07-02-【next-js】node-canvasでのogp動的生成でハマったポイント","collection":"blog","commitMessage":"Create Blog “2021-07-02-【next-js】node-canvasでのogp動的生成でハマったポイント”","title":"【Vercel】node-canvasでのOGP動的生成でハマったポイント","description":"No Description!","objects":{"entry":{"path":"_data/blog/2021-07-02-【next-js】node-canvasでのogp動的生成でハマったポイント.md","sha":"cd94d3be3ef5205f5d69ba7041f764d9952470b8"},"files":[]},"timeStamp":"2021-07-02T13:45:19.568Z","version":"1"}